email_hosts/__init__.py
email_hosts/backends.py
email_hosts/management/__init__.py
email_hosts/management/commands/__init__.py
email_hosts/management/commands/sendtestemailhosts.py
django_email_hosts-0.2.1.dist-info/METADATA
django_email_hosts-0.2.1.dist-info/WHEEL
django_email_hosts-0.2.1.dist-info/licenses/LICENSE
django_email_hosts-0.2.1.dist-info/RECORD
