Metadata-Version: 2.3
Name: django-email-hosts
Version: 0.2.1
Summary: Support for several SMTP configurations in a single site
Project-URL: Homepage, https://github.com/feinheit/django-email-hosts/
Author-email: Feinheit AG <dev@feinheit.ch>
License: BSD-3-Clause
License-File: LICENSE
Classifier: Environment :: Web Environment
Classifier: Framework :: Django
Classifier: Intended Audience :: Developers
Classifier: License :: OSI Approved :: BSD License
Classifier: Operating System :: OS Independent
Classifier: Programming Language :: Python
Classifier: Programming Language :: Python :: 3 :: Only
Classifier: Programming Language :: Python :: 3.9
Classifier: Programming Language :: Python :: 3.10
Classifier: Programming Language :: Python :: 3.11
Classifier: Programming Language :: Python :: 3.12
Requires-Python: >=3.9
Requires-Dist: django>=3.2
Requires-Dist: speckenv>=3.2
Provides-Extra: tests
Requires-Dist: coverage; extra == 'tests'
